{
  "title": [
    "А̄ма̄ра джīвана"
  ],
  "author": [
    "Шрīла Бгактівінод Тха̄кур"
  ],
  "subtitle": [],
  "verses": [
    {
      "number": "1",
      "text": [
        "а̄ма̄ра джīвана,    сада̄ па̄пе рата,",
        "    на̄хіко пуньєра лешя",
        "порере удвеґа,    діячхі дже кото,",
        "    діячхі джīвере клешя"
      ],
      "translation": [
        "Усе моє життя пронизане гріхами <br class=\"SongVerse__break\" />і навіть краплі доброчестя в ньому не знайти.<br class=\"SongVerse__break\" />Для інших душ я - джерело страждання.<br class=\"SongVerse__break\" />Лише турботи й біль я зміг їм принести."
      ]
    },
    {
      "number": "2",
      "text": [
        "ніджа сукха ла̄ґі’,    па̄пе на̄хі дорі,",
        "    дая-хīна сва̄ртха-паро",
        "пара-сукхе духкхī,    сада̄ мітхʼя-бга̄ши,",
        "    пара-духкха сукха-кара"
      ],
      "translation": [
        "Для власної утіхи я неприховано гріхи творив.<br class=\"SongVerse__break\" />Не здатний співчувати - себе я ставив вище інших.<br class=\"SongVerse__break\" />Я потонув в брехні. Страждаю я від радості у ближніх,<br class=\"SongVerse__break\" />а насолоджусюь - смакуючи їх біль."
      ]
    },
    {
      "number": "3",
      "text": [
        "ашєша ка̄мана̄,    хриді ма̄джге мора,",
        "    кродгī, дамбга-пара̄яна",
        "мада-матта сада̄,    вішоє мохіта,",
        "    хімса̄-ґарва вібгӯшана"
      ],
      "translation": [
        "В бездонну прірву для бажань перетворилось моє серце.<br class=\"SongVerse__break\" />Я повен гніву та пихи, пʼянить мене від марносластва.<br class=\"SongVerse__break\" />Я збитий з пантелику від чуттєвих насолод.<br class=\"SongVerse__break\" />Жорстокість та гординя - ось мої прикраси."
      ]
    },
    {
      "number": "4",
      "text": [
        "нідра̄ласья хата,    сука̄рдже вірата,",
        "    ака̄рдже удьйоґī а̄мі",
        "пратіштха ла̄ґія,    шятхʼя-а̄чарана,",
        "    лобга-хата сада̄ ка̄мī"
      ],
      "translation": [
        "Спустошений від ліні й сну я відкидаю всяке благочестя <br class=\"SongVerse__break\" />та з особливою жагою прагну до творіння зла.<br class=\"SongVerse__break\" />Брехнею здобуваю я мирські повагу й славу.<br class=\"SongVerse__break\" />Я - жадібності жертва і похоті постійний раб."
      ]
    },
    {
      "number": "5",
      "text": [
        "е хено дурджана,    саджджана-варджіта,",
        "    апара̄дгі нірантара",
        "шюбга-ка̄рджа-шюнья,    сада̄нартха-мана̄х,",
        "    на̄на̄ духкхе джара джара"
      ],
      "translation": [
        "Такий порочний грішник відторгнутий благочестивим людом.<br class=\"SongVerse__break\" />Наповнений зневагами, позбавлений благодіянь,<br class=\"SongVerse__break\" />завжди у настрої \"тільки собі й для себе\",<br class=\"SongVerse__break\" />ослаблений від безлічі страждань."
      ]
    },
    {
      "number": "6",
      "text": [
        "ба̄рдгакʼє екхона,    упа̄я-віхīна,",
        "    та̄’те дīна акіньчана",
        "бгакатівінода,    прабгура чаране,",
        "    коре духкха ніведана"
      ],
      "translation": [
        "Відтак, Бгактівінод на старості років <br class=\"SongVerse__break\" />позбавлений відрад, принижений й злиденний,<br class=\"SongVerse__break\" />до лотосових стоп Верховного Владики <br class=\"SongVerse__break\" />підносить зі смиренням печальну повість своїх літ."
      ]
    }
  ],
  "attributes": {
    "page": "161"
  }
}