{
  "title": [
    "Даинйатмика"
  ],
  "author": [
    "Ш́рӣла Бхактивинод Т̣ха̄кур"
  ],
  "subtitle": [],
  "verses": [
    {
      "number": "1",
      "text": [
        "(прабху хе!)",
        "эмона дурмати,    сам̇са̄ра бхиторе,",
        "    под̣ийа̄ а̄чхину а̄ми",
        "тава ниджа-джана,    коно маха̄джане",
        "    па̄т̣хāийа̄ диле туми"
      ],
      "translation": [
        "Порочный ум бросил меня в этот мир, о Господь, но один из Твоих чистых возвышенных преданных пришел, чтобы освободить меня!"
      ]
    },
    {
      "number": "2",
      "text": [
        "дойа̄ кори’ море,    патита декхийа̄,",
        "    кохило а̄ма̄ре гийа̄",
        "охе дӣна-джон,    ш́уно бха̄ло катха̄",
        "    улласита хо’бе хийа̄"
      ],
      "translation": [
        "Увидев меня, столь падшего и презренного, он сжалился надо мной и сказал: «Смиренная душа, выслушай благую весть и тогда твое сердце возрадуется!»"
      ]
    },
    {
      "number": "3",
      "text": [
        "тома̄ре та̄рите,    ш́рӣ-кр̣ш̣н̣а-чаитанйа,",
        "    навадвӣпе авата̄р",
        "тома̄ хено кото,    дӣна хӣна джоне",
        "    корилена бхава-па̄р"
      ],
      "translation": [
        "«Чтобы спасти тебя, Шри Кришна Чайтанья явился на земле Навадвипы. Он уже помог многим несчастным душам, таким как ты, благополучно пересечь пучину материального существования»."
      ]
    },
    {
      "number": "4",
      "text": [
        "ведера пратиджн̃а̄,    ра̄кхиба̄ра торе,",
        "    рукма-варн̣а випра-сута",
        "маха̄прабху на̄ме,    надӣйа̄ ма̄та̄йа",
        "    сон̇ге бха̄и авадхӯта"
      ],
      "translation": [
        "«Чтобы исполнить пророчество Вед, сын брахмана по имени Махапрабху, чье тело отливает золотом, пришел вместе со Своим братом <i class=\"SongVerse__term\">авадхутой</i> Нитьянандой. Вместе Они затопили Надию божественным экстазом»."
      ]
    },
    {
      "number": "5",
      "text": [
        "нанда сута джини,    чаитанйа госа̄и",
        "    ниджа-на̄ма кори’ да̄на",
        "та̄рило джагат,    туми-о джа̄ийа̄",
        "    лохо ниджа-паритра̄н̣а"
      ],
      "translation": [
        "«Шри Чайтанья, сам Кришна, спас этот мир, одаривая каждого Своим Святым Именем. Иди и обрети свободу!»"
      ]
    },
    {
      "number": "6",
      "text": [
        "се катха̄ ш́унийа̄    а̄сийа̄чхи, на̄тха!",
        "    тома̄ра чаран̣а-толе",
        "бхакативинода,    ка̐дийа̄ ка̐дийа̄,",
        "    а̄пана-ка̄хинӣ боле"
      ],
      "translation": [
        "О Господь, услышав эти слова, Бхактивинод зарыдал, моля о живительной сени Твоих лотосоподобных стоп и рассказывая историю своей жизни."
      ]
    }
  ],
  "embeds": [
    {
      "title": "Шрила Говинда Махарадж",
      "embed_code": "<iframe width=\"100%\" height=\"20\" scrolling=\"no\" frameborder=\"no\" allow=\"autoplay\" src=\"https://w.soundcloud.com/player/?url=https%3A%2F%2Fsoundcloud.com%2Fbharatimaharaj%2Fgovinda-maharaj-emona-durmati\"></iframe>"
    },
    {
      "title": "Шрила Шридхар Махарадж",
      "embed_code": "<iframe width=\"100%\" height=\"20\" scrolling=\"no\" frameborder=\"no\" allow=\"autoplay\" src=\"https://w.soundcloud.com/player/?url=https%3A%2F%2Fsoundcloud.com%2Fbharatimaharaj%2Fsridhar-maharaj-and-govinda-7\"></iframe>"
    },
    {
      "title": "Шрила Ачарья Махарадж",
      "embed_code": "<iframe width=\"100%\" height=\"20\" scrolling=\"no\" frameborder=\"no\" allow=\"autoplay\" src=\"https://w.soundcloud.com/player/?url=https%3A%2F%2Fsoundcloud.com%2Fbharatimaharaj%2Facharya-maharaj-emona-durmati\"></iframe>"
    },
    {
      "title": "Шрила Госвами Махарадж",
      "embed_code": "<iframe width=\"100%\" height=\"20\" scrolling=\"no\" frameborder=\"no\" allow=\"autoplay\" src=\"https://w.soundcloud.com/player/?url=https%3A%2F%2Fsoundcloud.com%2Fbharatimaharaj%2Fgoswami-maharaj-emona-durmati\"></iframe>"
    },
    {
      "title": "Навадвип Дхам",
      "embed_code": "<iframe width=\"100%\" height=\"20\" scrolling=\"no\" frameborder=\"no\" allow=\"autoplay\" src=\"https://w.soundcloud.com/player/?url=https%3A%2F%2Fsoundcloud.com%2Fbharatimaharaj%2Fnavadwip-scsm-emona-durmati\"></iframe>"
    },
    {
      "title": "Каракас Дхам",
      "embed_code": "<iframe width=\"100%\" height=\"20\" scrolling=\"no\" frameborder=\"no\" allow=\"autoplay\" src=\"https://w.soundcloud.com/player/?url=https%3A%2F%2Fsoundcloud.com%2Fbharatimaharaj%2Fshchsm-karakas-emona-durmati\"></iframe>"
    },
    {
      "title": "Сударшан Прабху",
      "embed_code": "<iframe width=\"100%\" height=\"20\" scrolling=\"no\" frameborder=\"no\" allow=\"autoplay\" src=\"https://w.soundcloud.com/player/?url=https%3A%2F%2Fsoundcloud.com%2Fbharatimaharaj%2Fsudarshan-prabhu-dainyatmika\"></iframe>"
    },
    {
      "title": "Шрила Авадхут Махарадж",
      "embed_code": "<iframe width=\"100%\" height=\"20\" scrolling=\"no\" frameborder=\"no\" allow=\"autoplay\" src=\"https://w.soundcloud.com/player/?url=https%3A%2F%2Fsoundcloud.com%2Fbharatimaharaj%2Favadxut-maxaradzh-emona\"></iframe>"
    },
    {
      "title": "Шрила Авадхут Махарадж",
      "embed_code": "<iframe width=\"100%\" height=\"20\" scrolling=\"no\" frameborder=\"no\" allow=\"autoplay\" src=\"https://w.soundcloud.com/player/?url=https%3A%2F%2Fsoundcloud.com%2Fbharatimaharaj%2Favadxut-maxaradzh-emona-1\"></iframe>"
    }
  ],
  "attributes": {
    "page": "154"
  }
}