{
  "title": [
    "Dainya Prārthanā Gīti"
  ],
  "author": [
    "by Śrīla Bhakti Vinod Ṭhākur"
  ],
  "subtitle": null,
  "verses": [
    {
      "number": "1",
      "text": [
        "kabe śrī chaitanya more karibena dayā",
        "kabe āmi pāiba vaiṣṇava-pada-chhāyā"
      ],
      "translation": [
        "When will Śrī Chaitanya be merciful to me? When will I reach the shade of the Vaiṣṇavas’ feet?"
      ]
    },
    {
      "number": "2",
      "text": [
        "kabe āmi chhāḍiba e viṣayābhimāna",
        "kabe viṣṇu-jane āmi kariba sammāna"
      ],
      "translation": [
        "When will I give up this mundane ego? When will I honour the Lord’s devotees?"
      ]
    },
    {
      "number": "3",
      "text": [
        "gala-vastra kṛtāñjali vaiṣṇava-nikaṭe",
        "dante tṛṇa kari’ dā̐ḍāiba niṣkapaṭe"
      ],
      "translation": [
        "With a cloth around my neck, joined palms, and straw between my teeth, I will sincerely submit myself at the Vaiṣṇava’s feet."
      ]
    },
    {
      "number": "4",
      "text": [
        "kā̐diyā kā̐diyā jānāiba duḥkha-grāma",
        "saṁsāra-anala haite māgiba viśrāma"
      ],
      "translation": [
        "Weeping, I will convey my sorrows to the Vaiṣṇava and pray for shelter from the fire of material existence."
      ]
    },
    {
      "number": "5",
      "text": [
        "śuniyā āmāra duḥkha vaiṣṇava ṭhākura",
        "āmā’ lāgi’ kṛṣṇe āvedibena prachura"
      ],
      "translation": [
        "Hearing of my sorrow, the worshippable Vaiṣṇava will thoroughly pray to Kṛṣṇa on my behalf."
      ]
    },
    {
      "number": "6",
      "text": [
        "vaiṣṇavera āvedane kṛṣṇa dayāmaya",
        "e hena pāmara prati habena sadaya"
      ],
      "translation": [
        "Satisfied by the Vaiṣṇava’s prayer, Kṛṣṇa will be merciful to this sinner."
      ]
    },
    {
      "number": "7",
      "text": [
        "vinodera nivedana vaiṣṇava-charaṇe",
        "kṛpā kari’ saṅge laha ei akiñchane"
      ],
      "translation": [
        "Bhakti Vinod prays at the feet of the Vaiṣṇavas: “Mercifully take this lowly soul with you.”"
      ]
    }
  ],
  "attributes": {
    "page": "34"
  }
}