{
  "title": [
    "Śrī Vaiṣṇava-mahimā-gīti"
  ],
  "author": [
    "by Śrīla Bhakti Vinod Ṭhākur"
  ],
  "subtitle": [],
  "verses": [
    {
      "number": "1",
      "text": [
        "(ohe) vaiṣṇava ṭhākura    dayāra sāgara",
        "    e dāse karuṇā kari",
        "diyā pada-chāyā    śodha he āmāya",
        "    tomāra charaṇa dhari"
      ],
      "translation": [
        "O worshippable Vaiṣṇava, ocean of grace, be merciful to this servant. Give me the shade of your feet and purify me. I clasp your feet."
      ],
      "word_by_word": []
    },
    {
      "number": "2",
      "text": [
        "chhaya vega dami’    chhaya doṣa śodhi’",
        "    chhaya guṇa deha’ dāse",
        "chhaya sat-saṅga    deha’ he āmāre",
        "    basechhi saṅgera āśe"
      ],
      "translation": [
        "Subjugate the six urges, rectify the six defects, and bestow the six good qualities upon this servant. Grant me the six kinds of good association. I have sat at your feet, desiring that association."
      ],
      "word_by_word": []
    },
    {
      "number": "3",
      "text": [
        "ekākī āmāra    nāhi pāya bala",
        "    hari-nāma-saṅkīrtane",
        "tumi kṛpā kari    śraddhā-bindu diyā",
        "    deha’ kṛṣṇa-nāma-dhane"
      ],
      "translation": [
        "Alone I do not have the ability to properly chant the Lord’s Name. Mercifully give me a drop of faith and bestow upon me the wealth of Kṛṣṇa’s Name."
      ],
      "word_by_word": []
    },
    {
      "number": "4",
      "text": [
        "kṛṣṇa se tomāra    kṛṣṇa dite pāra",
        "    tomāra śakati āchhe",
        "āmi ta’ kāṅgāla    ‘kṛṣṇa kṛṣṇa’ bali",
        "    dhāi tava pāchhe pāchhe"
      ],
      "translation": [
        "Kṛṣṇa is yours. You can give Kṛṣṇa. You have that power. I am very poor. Calling, ‘Kṛṣṇa!’ ‘Kṛṣṇa!’, I run after you."
      ],
      "word_by_word": []
    },
    {
      "number": null,
      "text": [
        "(āmi) (dhāi tava pāchhe pāchhe)",
        "(kṛṣṇa dhana pābar āśe    dhāi tava pāchhe pāchhe)",
        "(tumi dile kṛṣṇa dite pāra)",
        "(kṛṣṇa tomār hṛdayer dhan    tumi dileo dite pāra)",
        "(kṛṣṇa debār śakti-dhara    tumi dileo dite pāra)"
      ],
      "translation": [
        "I run after you. I run after you in hope of attaining the wealth of Kṛṣṇa. If you desire to give Kṛṣṇa, you can give Him. If you desire to give, you can give. Kṛṣṇa is the wealth of your heart. You have the power to give Kṛṣṇa. If only you desire to give Kṛṣṇa, you can give Him."
      ],
      "word_by_word": []
    }
  ],
  "attributes": {
    "page": "58"
  },
  "word_by_word": []
}